{
  "name": "boost",
  "version": "1.76.0",
  "license": {
    "type": "Boost Software License",
    "file": "LICENSE_1_0.txt"
  },
  "homepage": "http://www.boost.org",
  "summary": "Boost provides free peer-reviewed portable C++ source libraries.",
  "authors": "Rene Rivera",
  "source": {
    "http": "https://boostorg.jfrog.io/artifactory/main/release/1.76.0/source/boost_1_76_0.tar.bz2",
    "sha256": "5e89103d9b70bba5c91a794126b169cb67654be2051f90cf7c22ba6893ede0ff"
  },
  "platforms": {
    "ios": "13.4"
  },
  "requires_arc": false,
  "module_name": "boost",
  "header_dir": "boost",
  "preserve_paths": "boost"
}
